Workbook

Sheet Dashboard
A1: JobPilot — Dashboard
A2: © 2026 [YOUR NAME] · All rights reserved · 1000Jobs Final Stage submission
A4: BY STATUS | D4: HOW TO USE
A5: Total saved | B5: =COUNTIF(Tracker!N:N,"Saved") -> 1 | D5: 1. The agent appends new applications to the Tracker sheet.
A6: Total applied | B6: =COUNTIF(Tracker!N:N,"Applied")+COUNTIF(Tracker!N:N,"In Review")+COUNTIF(Tracker!N:N,"Phone Screen")+COUNTIF(Tracker!N:N,"Interview R1")+COUNTIF(Tracker!N:N,"Interview R2")+COUNTIF(Tracker!N:N,"Interview R3")+COUNTIF(Tracker!N:N,"Take-Home")+COUNTIF(Tracker!N:N,"Offer")+COUNTIF(Tracker!N:N,"Negotiating")+COUNTIF(Tracker!N:N,"Accepted")+COUNTIF(Tracker!N:N,"Rejected")+COUNTIF(Tracker!N:N,"Ghosted")+COUNTIF(Tracker!N:N,"Closed") -> 3 | D6: 2. Update Status as you progress — drop-downs are pre-filled.
A7: In active interview | B7: =COUNTIF(Tracker!N:N,"Phone Screen")+COUNTIF(Tracker!N:N,"Interview R1")+COUNTIF(Tracker!N:N,"Interview R2")+COUNTIF(Tracker!N:N,"Interview R3")+COUNTIF(Tracker!N:N,"Take-Home") -> 2 | D7: 3. For each interview, add a row to the Interview Rounds sheet.
A8: Offers received | B8: =COUNTIF(Tracker!N:N,"Offer")+COUNTIF(Tracker!N:N,"Negotiating")+COUNTIF(Tracker!N:N,"Accepted") -> 0 | D8: 4. Build your Story Bank as you interview. Aim for 5-10 strong stories.
A9: Rejected / ghosted | B9: =COUNTIF(Tracker!N:N,"Rejected")+COUNTIF(Tracker!N:N,"Ghosted") -> 0 | D9: 5. The dashboard updates live from formulas.
A10: Awaiting response | B10: =COUNTIF(Tracker!O:O,"Awaiting Response") -> 1
A11: Stale (>21 days) | B11: =COUNTIF(Tracker!Q:Q,">21") -> 0 | D11: STALE APPLICATIONS
D12: Any row with Days Since > 21 in the Tracker is auto-highlighted.
A13: FUNNEL | D13: Either follow up, or move it to Ghosted.
A14: Application → Interview rate | B14: =IFERROR((COUNTIF(Tracker!N:N,"Phone Screen")+COUNTIF(Tracker!N:N,"Interview R1")+COUNTIF(Tracker!N:N,"Interview R2")+COUNTIF(Tracker!N:N,"Interview R3")+COUNTIF(Tracker!N:N,"Offer")+COUNTIF(Tracker!N:N,"Negotiating")+COUNTIF(Tracker!N:N,"Accepted"))/B6,0) -> 0.66666667
A15: Interview → Offer rate | B15: =IFERROR((COUNTIF(Tracker!N:N,"Offer")+COUNTIF(Tracker!N:N,"Negotiating")+COUNTIF(Tracker!N:N,"Accepted"))/(COUNTIF(Tracker!N:N,"Phone Screen")+COUNTIF(Tracker!N:N,"Interview R1")+COUNTIF(Tracker!N:N,"Interview R2")+COUNTIF(Tracker!N:N,"Interview R3")+COUNTIF(Tracker!N:N,"Offer")+COUNTIF(Tracker!N:N,"Negotiating")+COUNTIF(Tracker!N:N,"Accepted")),0) -> 0 | D15: STORY BANK STRATEGY
A16: Average fit score (applied) | B16: =IFERROR(AVERAGEIFS(Tracker!K:K,Tracker!C:C,"<>"),0) -> 0.73666667 | D16: Review the Story Bank before each interview — pick 3-4 stories that fit
D17: the company's likely questions. After the interview, log which stories you used
A18: BY WORK MODE | D18: in the Interview Rounds sheet, then update Times Used in the Story Bank.
A19: Onsite | B19: =COUNTIF(Tracker!F:F,"onsite") -> 0
A20: Hybrid | B20: =COUNTIF(Tracker!F:F,"hybrid") -> 1
A21: Remote | B21: =COUNTIF(Tracker!F:F,"remote") -> 3
A22: Freelance | B22: =COUNTIF(Tracker!F:F,"freelance") -> 0

Sheet Tracker
A1: JobPilot — Application Tracker
A2: © 2026 [YOUR NAME] · All rights reserved · Submitted to 1000Jobs Final Stage for evaluation only · See LICENSE
A4: ID | B4: Date Saved | C4: Date Applied | D4: Company | E4: Role | F4: Work Mode | G4: Platform | H4: Job URL | I4: Location | J4: Salary Range | K4: Fit Score | L4: Archetype Match | M4: Resume Version | N4: Status | O4: Response | P4: Last Update | Q4: Days Since | R4: Recruiter / Contact | S4: Recruiter Email/LinkedIn | T4: Notes | U4: Run ID (logs)
A5: 1 | B5: 2026-04-28 | C5: 2026-04-29 | D5: Grammarly | E5: Senior Product Manager | F5: remote | G5: Greenhouse | H5: https://job-boards.greenhouse.io/grammarly/jobs/7767680 | I5: Remote · US | J5: $180-220k | K5: 0.82 | L5: women_forward + stable_provider | M5: v3-pm-grammarly | N5: Phone Screen | O5: Responded | P5: 2026-05-01 | Q5: =IF(P5="","",TODAY()-P5) -> 0 | R5: Sarah Chen | S5: sarah.chen@grammarly.com | T5: Recruiter very responsive. Mentioned WLB explicitly. Phone screen Mon 11am. | U5: run_2026-04-29T14-12-22Z_8f3a
A6: 2 | B6: 2026-04-25 | C6: 2026-04-26 | D6: Modern Health | E6: Senior PMM | F6: remote | G6: Greenhouse | H6: https://job-boards.greenhouse.io/modernhealth/jobs/8465250002 | I6: Remote · US | J6: $160-190k | K6: 0.78 | L6: women_forward + mission_believer | M6: v2-pmm-mh | N6: Interview R1 | O6: Responded | P6: 2026-04-30 | Q6: =IF(P6="","",TODAY()-P6) -> 1 | R6: Maya Patel | S6: maya@modernhealth.com | T6: Hiring manager loved the case study. R2 scheduled. | U6: run_2026-04-26T09-44-08Z_b21c
A7: 3 | B7: 2026-04-30 | C7: 2026-04-30 | D7: Geotab | E7: Senior PM, Go App | F7: remote | G7: Greenhouse | H7: https://job-boards.greenhouse.io/geotab/jobs/5041684008 | I7: Remote · CA | J7: $150-180k | K7: 0.61 | L7: stable_provider | M7: v3-pm-geotab | N7: Applied | O7: Awaiting Response | P7: 2026-04-30 | Q7: =IF(P7="","",TODAY()-P7) -> 1 | T7: Auto-applied via JobPilot. Below 0.7 archetype match — flagged. | U7: run_2026-04-30T16-02-44Z_c98d
A8: 4 | B8: 2026-04-22 | D8: Anthropic | E8: Member of Technical Staff | F8: hybrid | G8: Custom (anthropic.com/careers) | H8: https://www.anthropic.com/careers | I8: San Francisco | J8: $240-300k | K8: 0.55 | L8: deep_specialist | M8: v4-eng-anthropic | N8: Saved | O8: — | P8: 2026-04-22 | Q8: =IF(P8="","",TODAY()-P8) -> 9 | T8: Saved — need to network in before applying. Noted 2 SF-based connections on LinkedIn.
Q9: =IF(P9="","",TODAY()-P9)
Q10: =IF(P10="","",TODAY()-P10)
Q11: =IF(P11="","",TODAY()-P11)
Q12: =IF(P12="","",TODAY()-P12)
Q13: =IF(P13="","",TODAY()-P13)
Q14: =IF(P14="","",TODAY()-P14)
Q15: =IF(P15="","",TODAY()-P15)
Q16: =IF(P16="","",TODAY()-P16)
Q17: =IF(P17="","",TODAY()-P17)
Q18: =IF(P18="","",TODAY()-P18)
Q19: =IF(P19="","",TODAY()-P19)
Q20: =IF(P20="","",TODAY()-P20)
... Q58: =IF(P58="","",TODAY()-P58)

Sheet Interview Rounds
A1: Interview Rounds — Detail Log
A2: One row per interview round per application. Cross-reference Application ID with the Tracker sheet.
A4: App ID | B4: Company | C4: Role | D4: Round | E4: Round Type | F4: Date | G4: Time | H4: Duration (min) | I4: Interviewer Name | J4: Interviewer Title | K4: Interviewer LinkedIn | L4: Format | M4: Outcome | N4: Confidence | O4: Questions Asked | P4: What I Did Well | Q4: What I'd Improve | R4: Stories Used | S4: Follow-Up Sent? | T4: Thank-You Sent? | U4: Notes
A5: 1 | B5: Grammarly | C5: Senior PM | D5: R1 | E5: Phone Screen — Recruiter | F5: 2026-05-04 | G5: 11:00 | H5: 30 | I5: Sarah Chen | J5: Senior Recruiter | K5: linkedin.com/in/sarahchen-grammarly | L5: Phone | M5: Pass | N5: High | O5: Why Grammarly? What's your PM philosophy? Why remote? | P5: Articulated WLB priorities clearly. Story about Q3 launch landed. | Q5: Could have asked more about team structure. | R5: Q3 launch (story-1), team-restructuring (story-3) | S5: Yes | T5: Yes | U5: Sarah is moving me to HM round. Said comp range was confirmed.
A6: 2 | B6: Modern Health | C6: Senior PMM | D6: R1 | E6: Hiring Manager | F6: 2026-05-02 | G6: 14:00 | H6: 60 | I6: Maya Patel | J6: Director of Product Marketing | K6: linkedin.com/in/mayapatel | L6: Video | M6: Pass | N6: High | O6: Walk me through a launch. How do you think about positioning? Mental health POV? | P6: Strong launch case study. Genuine answer on mental health. | Q6: Got tripped up on segmentation question. Practice this. | R6: Q3 launch (story-1), product-positioning (story-2) | S6: Yes | T6: Yes | U6: Maya great — felt aligned. R2 with VP next week. Asked for case study brief.
A7: 2 | B7: Modern Health | C7: Senior PMM | D7: R2 | E7: VP / Skip-Level | F7: 2026-05-09 | G7: 11:00 | H7: 45 | I7: Jordan Lee | J7: VP Marketing | K7: linkedin.com/in/jordanlee | L7: Video | M7: Pending | N7: Medium | O7: Long-term GTM vision. Failure story. Why us over Calm? | P7: Failure story landed. Gave honest answer on competitor analysis. | Q7: Could have prepared a stronger 'why us over Calm'. | R7: Q3-launch-failed-experiment (story-4) | U7: Awaiting feedback. Maya said 'positive signals'.

Sheet Story Bank
A1: Story Bank — STAR + R
A2: Reusable behavioral interview stories. Inspired by career-ops by santifer. Aim for 5-10 strong stories that can be reshaped to answer most behavioral questions.
A4: Story ID | B4: Title | C4: Theme | D4: Situation | E4: Task | F4: Action | G4: Result | H4: Reflection | I4: Used In | J4: Times Used | K4: Strength (1-5) | L4: Refresh Date
A5: story-1 | B5: Q3 launch — pivoting under deadline | C5: Leadership / Adaptability | D5: Q3 2024, 4 weeks before our flagship launch, the eng team flagged that the ML inference cost would 5x in production vs staging. | E5: I owned the launch. Decision: cut features to hit cost target, or push date and risk competitor. | F5: Spent a day with eng to map cost vs feature impact. Cut two features that drove only 12% of value but 60% of cost. Communicated trade-off to exec team and to design. Negotiated with CFO for a soft cost ceiling rather than hard. | G5: Launched on time at 70% of feature scope. Cost came in 18% under target. Customer feedback was positive on launched features; the cut features later returned in v1.1. | H5: What I'd do differently: surface cost-of-inference earlier in the spec process. Now we run a 'cost diligence' check at design-review. | I5: Grammarly R1, Modern Health R1 | J5: 2 | K5: 5 | L5: 2026-04-28
A6: story-2 | B6: Product positioning vs incumbent | C6: Strategy / PMM | D6: Joined a team launching a category-creator product into a mature space dominated by an incumbent with 8x our budget. | E6: Define positioning that wouldn't get steamrolled. | F6: Researched 200 customer reviews of the incumbent — clustered into 3 unmet-need themes. Built positioning around the strongest theme ('built for teams of 10-50, not 1000+'). Validated with 12 customer calls before locking. | G6: Won 4 of 5 bake-offs vs incumbent in pilot quarter. Positioning held through GTM expansion. | H6: Customer reviews are an underused source of strategic insight. Now I do this on every new product I touch. | I6: Modern Health R1 | J6: 1 | K6: 4 | L6: 2026-04-28
A7: story-3 | B7: Restructuring a stuck team | C7: Leadership / People | D7: Inherited a team of 6 PMs with low morale, last to ship a feature 7 months earlier. | E7: Get them shipping again without an offsite or the 'inspirational speech' approach. | F7: 1:1s with each PM in week 1: pure listening, no advice. Found 4 of 6 had unclear scope. Re-cut scopes with each, made trade-offs explicit. Killed two stale projects publicly. | G7: First ship in week 5. By month 3, team velocity 2.5x. One PM left (good outcome — not aligned with new direction). | H7: Underrated lever: just making scope explicit. Most stuck teams aren't unmotivated, they're confused. | I7: Grammarly R1 | J7: 1 | K7: 5 | L7: 2026-04-28
A8: story-4 | B8: Failed experiment that I had to defend | C8: Failure / Reflection | D8: Ran an A/B test that I was sure would lift activation 10%. Designed, shipped, ran for 3 weeks. Result: -2% activation. | E8: Communicate the failure up the chain without burying it. | F8: Wrote a post-mortem the day results came in. Admitted my prior was wrong. Identified 2 confounders I should have caught upfront. Shared with the broader product org — not just my manager. | G8: Manager and skip-level both told me later they remembered the post-mortem more than my wins that quarter. Got promoted 6 months later partly on the strength of how I handled it. | H8: The willingness to publish your own failure publicly is a force multiplier. People remember it. | I8: Modern Health R2 | J8: 1 | K8: 4 | L8: 2026-04-28

Sheet Status Legend
A1: Status Legend
A2: Canonical statuses used by the Tracker dropdown. Color-coded.
A4: Status | B4: Description | C4: Color (text/bg)
A5: Saved | B5: Job saved but not yet applied | C5: #B8B5A6 on #FAFAF7
A6: Applied | B6: Application submitted | C6: #D97757 on #FCEEE6
A7: In Review | B7: Application acknowledged or under review | C7: #92400E on #FEF3C7
A8: Phone Screen | B8: Recruiter / HR initial call scheduled or done | C8: #92400E on #FEF3C7
A9: Interview R1 | B9: First-round interview (technical or hiring manager) | C9: #92400E on #FEF3C7
A10: Interview R2 | B10: Second-round interview (panel, deep dive, case) | C10: #92400E on #FEF3C7
A11: Interview R3 | B11: Third-round / final / leadership / executive | C11: #92400E on #FEF3C7
A12: Take-Home | B12: Take-home assignment in progress | C12: #92400E on #FEF3C7
A13: Offer | B13: Offer extended | C13: #1F4D3F on #E1ECE6
A14: Negotiating | B14: Offer received, negotiating terms | C14: #1F4D3F on #E1ECE6
A15: Accepted | B15: Offer accepted | C15: #1F4D3F on #E1ECE6
... A19: Closed | B19: Posting closed without outcome | C19: #4A4940 on #FAFAF7

Sheet Platforms
A1: Platform Reference
A2: Master list of supported and planned platforms. Filter by work mode + region.
A4: Platform | B4: Domain | C4: Kind | D4: Work Modes | E4: Regions | F4: Status | G4: Notes
A5: Greenhouse | B5: greenhouse.io | C5: ats | D5: onsite, hybrid, remote | E5: global | F5: live | G5: THE flagship adapter. Full v1 support.
A6: Glassdoor | B6: glassdoor.com | C6: aggregator | D6: onsite, hybrid, remote | E6: global | F6: stub | G6: We use Glassdoor primarily as a fit-intelligence source, not an application target.
A7: Indeed | B7: indeed.com | C7: aggregator | D7: onsite, hybrid, remote | E7: global | F7: planned | G7: High volume, low signal. Most listings are aggregated from elsewhere.
A8: LinkedIn | B8: linkedin.com/jobs | C8: aggregator | D8: onsite, hybrid, remote | E8: global | F8: planned | G8: Easy Apply varies wildly. Strong for onsite/hybrid roles. Bot-detection is heavy.
A9: eFinancialCareers | B9: efinancialcareers.com | C9: aggregator | D9: onsite, hybrid, remote | E9: global | F9: planned | G9: Finance / banking specialist board.
A10: Ashby | B10: ashbyhq.com | C10: ats | D10: onsite, hybrid, remote | E10: global | F10: planned
A11: Lever | B11: lever.co | C11: ats | D11: onsite, hybrid, remote | E11: global | F11: planned
A12: Workday | B12: myworkdayjobs.com | C12: ats | D12: onsite, hybrid, remote | E12: global | F12: planned | G12: Notoriously inconsistent. Each company customizes the form.
A13: Fiverr | B13: fiverr.com | C13: freelance | D13: freelance | E13: global | F13: planned | G13: Gig-based, supplier-side. The 'application' is creating a gig listing.
A14: Toptal | B14: toptal.com | C14: freelance | D14: freelance | E14: global | F14: planned | G14: Vetted freelance network. Application is invitation-based.
A15: Upwork | B15: upwork.com | C15: freelance | D15: freelance | E15: global | F15: planned | G15: Proposal-based, not application-based. Adapter logic differs significantly.
A16: Adecco | B16: adecco.ae | C16: recruiter | D16: onsite, hybrid | E16: AE, global | F16: planned
A17: Charterhouse | B17: charterhouseme.ae | C17: recruiter | D17: onsite, hybrid | E17: AE | F17: planned
A18: Cooper Fitch | B18: cooperfitch.ae | C18: recruiter | D18: onsite, hybrid | E18: AE | F18: planned
A19: Hays | B19: hays.ae | C19: recruiter | D19: onsite, hybrid | E19: AE, global | F19: planned
A20: MCG Talent | B20: mcgtalent.com | C20: recruiter | D20: onsite, hybrid | E20: AE | F20: planned
A21: Manpower | B21: manpower.ae | C21: recruiter | D21: onsite, hybrid | E21: AE, global | F21: planned
A22: Marc Ellis | B22: marcellis.com | C22: recruiter | D22: onsite, hybrid | E22: AE | F22: planned
A23: Michael Page | B23: michaelpage.ae | C23: recruiter | D23: onsite, hybrid | E23: AE, global | F23: planned
A24: Salt | B24: welovesalt.com | C24: recruiter | D24: onsite, hybrid, remote | E24: AE, global | F24: planned
A25: Bayt.com | B25: bayt.com | C25: regional | D25: onsite, hybrid | E25: AE, SA, EG, JO, LB | F25: planned
A26: GulfTalent | B26: gulftalent.com | C26: regional | D26: onsite, hybrid | E26: AE, SA, QA, KW, BH, OM | F26: planned
A27: Naukrigulf | B27: naukrigulf.com | C27: regional | D27: onsite, hybrid | E27: AE, SA, QA, KW, BH, OM | F27: planned | G27: The dominant Gulf job board. Onsite-heavy.
A28: FlexJobs | B28: flexjobs.com | C28: remote_first | D28: remote, freelance | E28: global | F28: planned | G28: Paid platform. Adapter would need credentials.
A29: Jobgether | B29: jobgether.com | C29: remote_first | D29: remote, hybrid | E29: global | F29: planned
A30: Jobspresso | B30: jobspresso.co | C30: remote_first | D30: remote | E30: global | F30: planned
A31: JustRemote | B31: justremote.co | C31: remote_first | D31: remote | E31: global | F31: planned
A32: Remote OK | B32: remoteok.com | C32: remote_first | D32: remote | E32: global | F32: planned | G32: Has a clean public JSON feed. Easiest to integrate.
A33: Remote.co | B33: remote.co | C33: remote_first | D33: remote | E33: global | F33: planned
A34: Remotive | B34: remotive.com | C34: remote_first | D34: remote | E34: global | F34: planned
A35: We Work Remotely | B35: weworkremotely.com | C35: remote_first | D35: remote | E35: global | F35: planned
A36: Web3 Jobs | B36: web3.career | C36: remote_first | D36: remote | E36: global | F36: planned
A37: Wellfound (formerly AngelList) | B37: wellfound.com | C37: remote_first | D37: remote, hybrid, onsite | E37: global | F37: planned | G37: Best for startup roles. Equity transparency.
A38: Working Nomads | B38: workingnomads.com | C38: remote_first | D38: remote | E38: global | F38: planned
